binarychain.py
binarychain-0.9.0.dist-info/LICENSE
binarychain-0.9.0.dist-info/METADATA
binarychain-0.9.0.dist-info/WHEEL
binarychain-0.9.0.dist-info/top_level.txt
binarychain-0.9.0.dist-info/RECORD
