Metadata-Version: 2.1
Name: binarychain
Version: 0.9.0
Summary: A simple but flexible binary container format, primarily meant for sending blocks of binary data over streaming interfaces like sockets. Similar to NetStrings, but for binary data.
Author-email: Rasjid Wilcox <rasjidw@openminddev.net>
License-File: LICENSE
Provides-Extra: dev
Requires-Dist: pytest ; extra == 'dev'
